mgtwriteusb/__init__.py
mgtwriteusb/samdos9
mgtwriteusb/writeusb.py
mgtwriteusb-0.9.3.data/data/share/doc/mgtwriteusb/ReadMe.md
mgtwriteusb-0.9.3.dist-info/licenses/License.txt
mgtwriteusb-0.9.3.dist-info/METADATA
mgtwriteusb-0.9.3.dist-info/WHEEL
mgtwriteusb-0.9.3.dist-info/entry_points.txt
mgtwriteusb-0.9.3.dist-info/top_level.txt
mgtwriteusb-0.9.3.dist-info/RECORD
