Metadata-Version: 2.4
Name: mgtwriteusb
Version: 0.9.3
Summary: Write SAM Coupé disk images to USB floppy drive
Author-email: Simon Owen <simon@simonowen.com>
License-Expression: MIT
Project-URL: Homepage, https://github.com/simonowen/writeusb
Project-URL: Source Code, https://github.com/simonowen/writeusb
Keywords: mgt,disk,sam,coupe,usb,floppy
Classifier: Development Status :: 4 - Beta
Classifier: Environment :: Console
Classifier: Operating System :: Microsoft :: Windows
Classifier: Operating System :: POSIX :: Linux
Classifier: Operating System :: MacOS
Classifier: Programming Language :: Python
Classifier: Programming Language :: Python :: 3
Classifier: Programming Language :: Python :: 3 :: Only
Classifier: Programming Language :: Python :: 3.9
Classifier: Programming Language :: Python :: 3.10
Classifier: Programming Language :: Python :: 3.11
Classifier: Programming Language :: Python :: 3.12
Classifier: Programming Language :: Python :: 3.13
Classifier: Topic :: System :: Filesystems
Classifier: Topic :: Utilities
Requires-Python: >=3.9
License-File: License.txt
Requires-Dist: mgtdisklib<0.6.0
Requires-Dist: pywin32>=311; platform_system == "Windows"
Dynamic: license-file
